zhongyao_mcp_server/__init__.py
zhongyao_mcp_server/testmoviepy.py
zhongyao_mcp_server/zhongyao_mcp_server.py
zhongyao_mcp_server/zhongyao_mcp_server1.py
zhongyao_mcp_server/zhongyao_mcp_server2.py
zhongyao_mcp_server/zhongyao_mcp_server3.py
zhongyao_mcp_server/zhongyao_mcp_server_sse.py
zhongyao_mcp_server-0.0.5.dist-info/METADATA
zhongyao_mcp_server-0.0.5.dist-info/WHEEL
zhongyao_mcp_server-0.0.5.dist-info/entry_points.txt
zhongyao_mcp_server-0.0.5.dist-info/RECORD
