Metadata-Version: 2.4
Name: zhongyao-mcp-server
Version: 0.0.5
Summary: 主要实现的是火山引擎的提供的中药文生图，文生视频，使用免费edgett实现文生音频，整合打包合成打包视频MCP-Server
Author-email: zhouqingyu666 <zhouqingyu666@aisino.com>
Requires-Python: >=3.11
Requires-Dist: configparser
Requires-Dist: cos-python-sdk-v5==1.9.33
Requires-Dist: httpx
Requires-Dist: mcp[cli]>=1.9.4
Requires-Dist: moviepy==1.0.3
Requires-Dist: openai>=1.86.0
Requires-Dist: requests>=2.31.0
Requires-Dist: sse-starlette
Requires-Dist: uvicorn
